Metadata-Version: 2.1
Name: HolaRivworks
Version: 1.0.0
Summary: just saying hello
Home-page: https://github.com/rivworks/hello-mundo
Author: j rivera
Author-email: joerivera@rivworks.net
License: UNKNOWN
Platform: UNKNOWN
